{
   "name"   : "DateRange",
   "title"  : "Диапазон дат",
   "version": "1.0",
   "spec"   : "1.0",
   "properties": {
      "ws-config":{
         "title":"Базовая конфигурация",
         "options":{
            "name": {
               "title": "Имя компонента",
               "type": "string"
            },
            "enable" : {
               "title" : "Разрешен ли элемент управления (возможно взаимодействие с ним)",
               "type" : "boolean",
               "default" : true
            },
            "allowChangeEnable" : {
               "title" : "Позволить менять состояние",
               "type" : "boolean",
               "default" : true
            },
            "hidden" : {
               "title" : "Скрыть компонент",
               "type" : "boolean",
               "default" : false
            },
            "tooltip" : {
               "title" : "Текст всплывающей подсказки",
               "default" : ""
            },
            "dateFromName": {
               "title": "Имя контрола, который отображает дату 'с'",
               "type": "string"
            },
            "dateToName": {
               "title": "Имя контрола, который отображает дату 'по'",
               "type": "string"
            },
            "dateFromValue": {
               "title": "Начальное значение даты начала интервала",
               "type": "string"
            },
            "dateToValue": {
               "title": "Начальное значение даты конца интервала",
               "type": "string"
            },
            "validators": {
               "title": "валидаторы",
               "type": "array"
            },
            "textView": {
               "title": "Отображать ли поле в виде текста",
               "type": "boolean",
               "default": false
            }
         }
      },
      "ws-handlers": {
         "title": "Обработчики",
         "options": {
            "onInit": {
               "title": "после инициализации",
               "type": "handler"
            },
            "onDestroy": {
               "title": "при разрушении",
               "type": "handler"
            },
            "onReady": {
               "title": "при готовности",
               "type": "handler"
            },
            "onChange": {
               "title": "при смене выбранного диапозона дат",
               "editor": "handler"
            },
            "onMenuHide": {
               "title": "Событие закрытия меню",
               "editor": "handler"
            }
         }
      }
   }
}